grobid_client/__init__.py
grobid_client/client.py
grobid_client/grobid_client.py
grobid_client/format/TEI2LossyJSON.py
grobid_client/format/TEI2LossyJSON_cli.py
grobid_client/format/TEI2Markdown.py
grobid_client/format/TEI2Markdown_cli.py
grobid_client/format/__init__.py
grobid_client/format/__main__.py
grobid_client/format/validate_json_refs.py
grobid_client_python-0.1.3.dist-info/METADATA
grobid_client_python-0.1.3.dist-info/WHEEL
grobid_client_python-0.1.3.dist-info/entry_points.txt
grobid_client_python-0.1.3.dist-info/top_level.txt
grobid_client_python-0.1.3.dist-info/RECORD
