Metadata-Version: 2.4
Name: grobid-client-python
Version: 0.1.3
Summary: Simple python client for GROBID REST services
Author-email: Patrice Lopez <patrice.lopez@science-miner.com>
Maintainer-email: Patrice Lopez <patrice.lopez@science-miner.com>, Luca Foppiano <lucanoro@duck.com>
License: 
Project-URL: Homepage, https://github.com/kermitt2/grobid_client_python
Project-URL: Repository, https://github.com/kermitt2/grobid_client_python
Project-URL: Changelog, https://github.com/kermitt2/grobid_client_python
Requires-Dist: requests
Requires-Dist: dateparser
Requires-Dist: beautifulsoup4
Requires-Dist: lxml
